{
	"info": {
		"_postman_id": "50b0c94f-8638-4e5b-a886-8ed7b6c3caaf",
		"name": "Showroom",
		"schema": "https://schema.getpostman.com/json/collection/v2.1.0/collection.json",
		"_exporter_id": "29806303"
	},
	"item": [
		{
			"name": "Get clothes (all or by name)",
			"request": {
				"method": "GET",
				"header": [],
				"url": {
					"raw": "http://localhost:8080/api/clothes",
					"protocol": "http",
					"host": [
						"localhost"
					],
					"port": "8080",
					"path": [
						"api",
						"clothes"
					],
					"query": [
						{
							"key": "name",
							"value": "2018",
							"disabled": true
						}
					]
				}
			},
			"response": []
		},
		{
			"name": "Post new garment",
			"request": {
				"method": "POST",
				"header": [],
				"body": {
					"mode": "raw",
					"raw": "{\n    \"name\": \"Remera de Racing\",\n    \"type\": \"Remera\",\n    \"brand\": \"Kappa\",\n    \"color\": \"Negra\",\n    \"size\": \"l\",\n    \"stock\": 100,\n    \"sell_price\": 200.0\n}",
					"options": {
						"raw": {
							"language": "json"
						}
					}
				},
				"url": {
					"raw": "http://localhost:8080/api/clothes",
					"protocol": "http",
					"host": [
						"localhost"
					],
					"port": "8080",
					"path": [
						"api",
						"clothes"
					]
				}
			},
			"response": []
		},
		{
			"name": "Get garment by id",
			"request": {
				"method": "GET",
				"header": [],
				"url": {
					"raw": "http://localhost:8080/api/clothes/2",
					"protocol": "http",
					"host": [
						"localhost"
					],
					"port": "8080",
					"path": [
						"api",
						"clothes",
						"2"
					]
				}
			},
			"response": []
		},
		{
			"name": "Delete garment by id",
			"request": {
				"method": "DELETE",
				"header": [],
				"url": {
					"raw": "http://localhost:8080/api/clothes/52",
					"protocol": "http",
					"host": [
						"localhost"
					],
					"port": "8080",
					"path": [
						"api",
						"clothes",
						"52"
					]
				}
			},
			"response": []
		},
		{
			"name": "Get garment by size",
			"request": {
				"method": "GET",
				"header": [],
				"url": {
					"raw": "http://localhost:8080/api/clothes/size/l",
					"protocol": "http",
					"host": [
						"localhost"
					],
					"port": "8080",
					"path": [
						"api",
						"clothes",
						"size",
						"l"
					]
				}
			},
			"response": []
		},
		{
			"name": "Patch garment by id",
			"request": {
				"method": "PUT",
				"header": [],
				"body": {
					"mode": "raw",
					"raw": "    {\n        \"name\": \"Remera del Bicho\",\n        \"type\": \"Remera\",\n        \"brand\": \"Nike\",\n        \"color\": \"Rojo\",\n        \"size\": \"l\",\n        \"stock\": 10000000,\n        \"sell_price\": 200.0\n    }",
					"options": {
						"raw": {
							"language": "json"
						}
					}
				},
				"url": {
					"raw": "http://localhost:8080/api/clothes/152",
					"protocol": "http",
					"host": [
						"localhost"
					],
					"port": "8080",
					"path": [
						"api",
						"clothes",
						"152"
					]
				}
			},
			"response": []
		}
	]
}